hk_libs/HKDict.py
hk_libs/HKPrint.py
hk_libs/__init__.py
hk_libs-1.2.1.dist-info/METADATA
hk_libs-1.2.1.dist-info/WHEEL
hk_libs-1.2.1.dist-info/top_level.txt
hk_libs-1.2.1.dist-info/RECORD
