Metadata-Version: 2.1
Name: hk-libs
Version: 1.2.1
Summary: Python library by Heekang Park
Home-page: https://github.com/HeekangPark/hk_libs
Author: Heekang Park
Author-email: park.heekang33@gmail.com
License: MIT
Classifier: Programming Language :: Python :: 3
Classifier: License :: OSI Approved :: MIT License
Classifier: Operating System :: OS Independent
Requires-Python: >=3
